plaid/__init__.py
plaid/data_containers.py
plaid/dialogs.py
plaid/io.py
plaid/misc.py
plaid/nexus.py
plaid/plaid.py
plaid/plot_widgets.py
plaid/reference.py
plaid/resources.py
plaid/trees.py
plaid/ufp_temp.py
plaid_xrd-1.0.0.dist-info/licenses/LICENSE
plaid_xrd-1.0.0.dist-info/METADATA
plaid_xrd-1.0.0.dist-info/WHEEL
plaid_xrd-1.0.0.dist-info/entry_points.txt
plaid_xrd-1.0.0.dist-info/top_level.txt
plaid_xrd-1.0.0.dist-info/RECORD
