Metadata-Version: 2.4
Name: plaid-xrd
Version: 1.0.0
Summary: plaid is a simple visualization tool intended to quickly evaluate azimuthally integrated powder diffraction data
Home-page: https://github.com/fgjorup/plaid
Author: Frederik H Gjørup
Author-email: fgjorup@chem.au.dk
License: GPL-3.0
Classifier: Programming Language :: Python :: 3
Classifier: Operating System :: OS Independent
Classifier: Intended Audience :: Science/Research
Classifier: Topic :: Scientific/Engineering :: Visualization
Requires-Python: >=3.9
License-File: LICENSE
Requires-Dist: numpy
Requires-Dist: h5py
Requires-Dist: PyQt6>=6.8.1
Requires-Dist: pyqtgraph>=0.13.7
Requires-Dist: Dans-Diffraction>=3.0.0
Requires-Dist: requests>=2.25.0
Requires-Dist: packaging>=20.0
Dynamic: author
Dynamic: author-email
Dynamic: classifier
Dynamic: description
Dynamic: description-content-type
Dynamic: home-page
Dynamic: license
Dynamic: license-file
Dynamic: requires-dist
Dynamic: requires-python
Dynamic: summary
